pylibcheck/__init__.py
pylibcheck-0.2.2.dist-info/LICENSE
pylibcheck-0.2.2.dist-info/METADATA
pylibcheck-0.2.2.dist-info/WHEEL
pylibcheck-0.2.2.dist-info/top_level.txt
pylibcheck-0.2.2.dist-info/RECORD
