Metadata-Version: 2.1
Name: pylibcheck
Version: 0.2.2
Summary: Simple library to check if packages are installed and install them for you
Home-page: https://github.com/rdimo/pylibcheck
Author: Rdimo
Author-email: <contact.rdimo@gmail.com>
License: UNKNOWN
Project-URL: Bug Tracker, https://github.com/rdimo/pylibcheck/issues
Keywords: pylibcheck,python,package,library,lib,module,checker
Platform: UNKNOWN
Classifier: Intended Audience :: Developers
Classifier: Programming Language :: Python :: 3
Classifier: License :: OSI Approved :: MIT License
Classifier: Operating System :: OS Independent
License-File: LICENSE
